{
    "id": "AS2011008",
    "profile": {
        "name": {
            "salutation": "Dr",
            "first": "Kulkarni",
            "last": "Amol A",
            "display": "Kulkarni, Dr Amol A"
        },
        "sex": "M",
        "birthDate": "1976-12-03"
    },
    "associate": {
        "type": "former",
        "yearelected": "2011",
        "period": "2011-2014"
    },
    "contact": {
        "address": "Chemical Engineering Division, NCL",
        "city": "Pune 411 008",
        "email": {
            "official": "aa.kulkarni@ncl.res.in"
        }
    }
}