{
    "id": "FL1944005",
    "profile": {
        "name": {
            "first": "Nedumangattu Kesava",
            "last": "Panikkar",
            "display": "Panikkar,  Nedumangattu Kesava"
        },
        "sex": "M",
        "birthDate": "1913-05-17",
        "deathDate": "1977-06-24",
        "honours": "FNA, FNASc"
    },
    "fellowship": {
        "type": "deceased",
        "section": "Animal Sciences",
        "yearelected": "1944",
        "councilservice": "1962-67; Vice President 1965-67"
    }
}