{
    "id": "FL2011022",
    "profile": {
        "name": {
            "salutation": "Dr.",
            "first": "Doraiswamy",
            "last": "Shankar",
            "display": "Shankar, Dr Doraiswamy"
        },
        "sex": "M",
        "birthDate": "1967-08-09",
        "degree": "Ph.D. (Goa)",
        "honours": "FNASc",
        "specialization": "Tropical Ocean Dynamics, Ocean-Atmospheric Interactions"
    },
    "fellowship": {
        "type": "current",
        "section": "Earth & Planetary Sciences",
        "yearelected": "2011"
    },
    "contact": {
        "address": "National Institute of Oceanography",
        "city": "Dona Paula 403 004",
        "state": "Goa",
        "telephone": {
            "office": "(0832) 245 0312",
            "residence": "(0832) 246 4516",
            "mobile": "94233 19557",
            "fax": "(0832) 245 0603"
        },
        "email": {
            "official": "shankar@nio.org",
            "personal": "dshankar67@gmail.com"
        }
    }
}