{
    "id": "FL2008022",
    "profile": {
        "name": {
            "salutation": "Dr.",
            "first": "Veena Krishnaji",
            "last": "Parnaik",
            "display": "Parnaik, Dr Veena Krishnaji"
        },
        "sex": "F",
        "birthDate": "1953-08-22",
        "degree": "Ph.D. (Ohio State)",
        "honours": "FNA",
        "specialization": "Cell Biology, Molecular Biology, Lamins and Nuclear Organisation"
    },
    "fellowship": {
        "type": "current",
        "section": "Animal Sciences",
        "yearelected": "2008"
    },
    "contact": {
        "address": "INSA Senior Scientist, Centre for Cellular & Molecular Biology, Uppal Road",
        "city": "Hyderabad 500 007",
        "state": "A.P.",
        "telephone": {
            "office": "(040) 2719 2614",
            "mobile": "98850 86220",
            "fax": "(040) 2716 0591"
        },
        "email": {
            "official": "veenap@ccmb.res.in"
        }
    }
}